Metadata-Version: 1.0
Name: brynq-sdk-mandrill
Version: 3.0.1
Summary: Mandrill wrapper from BrynQ
Home-page: UNKNOWN
Author: BrynQ
Author-email: support@brynq.com
License: BrynQ License
Platform: UNKNOWN
